com_vitalai_haleyai_question_domain/__init__.py
com_vitalai_haleyai_question_domain/domain-ontology/haley-ai-question-0.1.0.owl
com_vitalai_haleyai_question_domain/model/DomainOntology.py
com_vitalai_haleyai_question_domain/model/Edge_hasAlternateText.py
com_vitalai_haleyai_question_domain/model/Edge_hasAlternateText.pyi
com_vitalai_haleyai_question_domain/model/Edge_hasAnswer.py
com_vitalai_haleyai_question_domain/model/Edge_hasAnswer.pyi
com_vitalai_haleyai_question_domain/model/Edge_hasAnswerConstraint.py
com_vitalai_haleyai_question_domain/model/Edge_hasAnswerConstraint.pyi
com_vitalai_haleyai_question_domain/model/Edge_hasAnswerDependency.py
com_vitalai_haleyai_question_domain/model/Edge_hasAnswerDependency.pyi
com_vitalai_haleyai_question_domain/model/Edge_hasAnswerGroupDependency.py
com_vitalai_haleyai_question_domain/model/Edge_hasAnswerGroupDependency.pyi
com_vitalai_haleyai_question_domain/model/Edge_hasAnswerInstance.py
com_vitalai_haleyai_question_domain/model/Edge_hasAnswerInstance.pyi
com_vitalai_haleyai_question_domain/model/Edge_hasAnswerInstanceDerivation.py
com_vitalai_haleyai_question_domain/model/Edge_hasAnswerInstanceDerivation.pyi
com_vitalai_haleyai_question_domain/model/Edge_hasAnswerInstanceDerivationRuleInvocation.py
com_vitalai_haleyai_question_domain/model/Edge_hasAnswerInstanceDerivationRuleInvocation.pyi
com_vitalai_haleyai_question_domain/model/Edge_hasAnswerOption.py
com_vitalai_haleyai_question_domain/model/Edge_hasAnswerOption.pyi
com_vitalai_haleyai_question_domain/model/Edge_hasAnswerOptionDependency.py
com_vitalai_haleyai_question_domain/model/Edge_hasAnswerOptionDependency.pyi
com_vitalai_haleyai_question_domain/model/Edge_hasAnswerOptionLongDependency.py
com_vitalai_haleyai_question_domain/model/Edge_hasAnswerOptionLongDependency.pyi
com_vitalai_haleyai_question_domain/model/Edge_hasAnswerOptionValueDependency.py
com_vitalai_haleyai_question_domain/model/Edge_hasAnswerOptionValueDependency.pyi
vital_ai_haley_question-0.1.6.dist-info/METADATA
vital_ai_haley_question-0.1.6.dist-info/WHEEL
vital_ai_haley_question-0.1.6.dist-info/entry_points.txt
vital_ai_haley_question-0.1.6.dist-info/top_level.txt
vital_ai_haley_question-0.1.6.dist-info/RECORD
